llama_index/llms/fireworks/__init__.py
llama_index/llms/fireworks/base.py
llama_index/llms/fireworks/utils.py
llama_index_llms_fireworks-0.4.4.dist-info/METADATA
llama_index_llms_fireworks-0.4.4.dist-info/WHEEL
llama_index_llms_fireworks-0.4.4.dist-info/licenses/LICENSE
llama_index_llms_fireworks-0.4.4.dist-info/RECORD
