Metadata-Version: 2.4
Name: llama-index-llms-fireworks
Version: 0.4.4
Summary: llama-index llms fireworks integration
Author: benjibc
License-Expression: MIT
License-File: LICENSE
Requires-Python: <4.0,>=3.9
Requires-Dist: llama-index-core<0.15,>=0.14.3
Requires-Dist: llama-index-llms-openai<0.7,>=0.6.0
